{
  "000074": {
    "warp_id": 0,
    "appearance_id": 0,
    "camera_id": 0
  },
  "000076": {
    "warp_id": 1,
    "appearance_id": 1,
    "camera_id": 0
  },
  "000077": {
    "warp_id": 2,
    "appearance_id": 2,
    "camera_id": 0
  },
  "000078": {
    "warp_id": 3,
    "appearance_id": 3,
    "camera_id": 0
  },
  "000091": {
    "warp_id": 4,
    "appearance_id": 4,
    "camera_id": 0
  },
  "000092": {
    "warp_id": 5,
    "appearance_id": 5,
    "camera_id": 0
  },
  "000093": {
    "warp_id": 6,
    "appearance_id": 6,
    "camera_id": 0
  },
  "000094": {
    "warp_id": 7,
    "appearance_id": 7,
    "camera_id": 0
  },
  "000095": {
    "warp_id": 8,
    "appearance_id": 8,
    "camera_id": 0
  },
  "000073": {
    "warp_id": 0,
    "appearance_id": 0,
    "camera_id": 0
  }
}